brevitas/__init__.py
brevitas/common.py
brevitas/config.py
brevitas/jit.py
brevitas/core/__init__.py
brevitas/core/restrict_val.py
brevitas/core/utils.py
brevitas/core/zero_point.py
brevitas/core/bit_width/__init__.py
brevitas/core/bit_width/const.py
brevitas/core/bit_width/parameter.py
brevitas/core/function_wrapper/__init__.py
brevitas/core/function_wrapper/clamp.py
brevitas/core/function_wrapper/misc.py
brevitas/core/function_wrapper/ops_ste.py
brevitas/core/function_wrapper/shape.py
brevitas/core/quant/__init__.py
brevitas/core/quant/binary.py
brevitas/core/quant/delay.py
brevitas/core/quant/int.py
brevitas/core/quant/int_base.py
brevitas/core/quant/ternary.py
brevitas/core/scaling/__init__.py
brevitas/core/scaling/int_scaling.py
brevitas/core/scaling/runtime.py
brevitas/core/scaling/standalone.py
brevitas/core/stats/__init__.py
brevitas/core/stats/stats_op.py
brevitas/core/stats/stats_wrapper.py
brevitas/core/stats/view_wrapper.py
brevitas/csrc/autograd_ste_ops.cpp
brevitas/export/__init__.py
brevitas/export/handler.py
brevitas/export/manager.py
brevitas/export/onnx/__init__.py
brevitas/export/onnx/debug.py
brevitas/export/onnx/handler.py
brevitas/export/onnx/manager.py
brevitas/export/onnx/finn/__init__.py
brevitas/export/onnx/finn/manager.py
brevitas/export/onnx/finn/transform.py
brevitas/export/onnx/finn/utils.py
brevitas/export/onnx/finn/function/__init__.py
brevitas/export/onnx/finn/function/acc.py
brevitas/export/onnx/finn/function/act.py
brevitas/export/onnx/finn/function/parameter.py
brevitas/export/onnx/finn/handler/__init__.py
brevitas/export/onnx/finn/handler/acc.py
brevitas/export/onnx/finn/handler/act.py
brevitas/export/onnx/finn/handler/base.py
brevitas/export/onnx/finn/handler/parameter.py
brevitas/export/onnx/qonnx/__init__.py
brevitas/export/onnx/qonnx/function.py
brevitas/export/onnx/qonnx/handler.py
brevitas/export/onnx/qonnx/manager.py
brevitas/export/onnx/standard/__init__.py
brevitas/export/onnx/standard/function.py
concrete_ml_extensions_brevitas-0.1.0.dist-info/LICENSE
concrete_ml_extensions_brevitas-0.1.0.dist-info/METADATA
concrete_ml_extensions_brevitas-0.1.0.dist-info/WHEEL
concrete_ml_extensions_brevitas-0.1.0.dist-info/entry_points.txt
concrete_ml_extensions_brevitas-0.1.0.dist-info/top_level.txt
concrete_ml_extensions_brevitas-0.1.0.dist-info/RECORD
