Metadata-Version: 2.1
Name: concrete-ml-extensions-brevitas
Version: 0.1.0
Summary: Quantization-aware training in PyTorch
Home-page: https://github.com/zama-ai/brevitas
Author: Andrei Stoian
Author-email: andrei.stoian@zama.ai
Requires-Python: >=3.6
License-File: LICENSE
Requires-Dist: torch (>=1.5.0)
Requires-Dist: packaging
Requires-Dist: setuptools
Requires-Dist: future-annotations
Requires-Dist: dependencies (==2.0.1)
Requires-Dist: typing-extensions (>=3.7.4)
Requires-Dist: dataclasses ; python_version < "3.7"
Provides-Extra: export
Requires-Dist: onnx ; extra == 'export'
Requires-Dist: onnxoptimizer ; extra == 'export'
Provides-Extra: finn_integration_ge_pt150
Requires-Dist: torch (>=1.5.0) ; extra == 'finn_integration_ge_pt150'
Requires-Dist: bitstring ; extra == 'finn_integration_ge_pt150'
Requires-Dist: toposort ; extra == 'finn_integration_ge_pt150'
Requires-Dist: qonnx ; extra == 'finn_integration_ge_pt150'
Requires-Dist: onnxruntime ; extra == 'finn_integration_ge_pt150'
Requires-Dist: onnx ; extra == 'finn_integration_ge_pt150'
Requires-Dist: onnxoptimizer ; extra == 'finn_integration_ge_pt150'
Provides-Extra: finn_integration_lt_pt150
Requires-Dist: torch (<1.5.0) ; extra == 'finn_integration_lt_pt150'
Requires-Dist: bitstring ; extra == 'finn_integration_lt_pt150'
Requires-Dist: finn-base ; extra == 'finn_integration_lt_pt150'
Requires-Dist: toposort ; extra == 'finn_integration_lt_pt150'
Requires-Dist: onnxruntime (==1.4.0) ; extra == 'finn_integration_lt_pt150'
Requires-Dist: onnxoptimizer ; extra == 'finn_integration_lt_pt150'
Requires-Dist: onnx (==1.5.0) ; (python_version < "3.8" or sys_platform == "linux") and extra == 'finn_integration_lt_pt150'
Requires-Dist: onnx (==1.7.0) ; (python_version >= "3.8" and sys_platform != "linux") and extra == 'finn_integration_lt_pt150'
Provides-Extra: hadamard
Requires-Dist: scipy ; extra == 'hadamard'
Provides-Extra: notebook
Requires-Dist: jupyter ; extra == 'notebook'
Requires-Dist: nbmake ; extra == 'notebook'
Provides-Extra: ort_integration
Requires-Dist: onnxruntime ; extra == 'ort_integration'
Requires-Dist: onnx ; extra == 'ort_integration'
Requires-Dist: onnxoptimizer ; extra == 'ort_integration'
Provides-Extra: stt
Requires-Dist: pillow (>=4.3.0) ; extra == 'stt'
Requires-Dist: ruamel.yaml ; extra == 'stt'
Requires-Dist: requests ; extra == 'stt'
Requires-Dist: librosa ; extra == 'stt'
Requires-Dist: inflect ; extra == 'stt'
Requires-Dist: unidecode ; extra == 'stt'
Requires-Dist: torch-stft ; extra == 'stt'
Requires-Dist: sox ; extra == 'stt'
Requires-Dist: tqdm ; extra == 'stt'
Requires-Dist: soundfile ; extra == 'stt'
Requires-Dist: numba (<=0.49.1) ; extra == 'stt'
Provides-Extra: test
Requires-Dist: pytest ; extra == 'test'
Requires-Dist: pytest-cases ; extra == 'test'
Requires-Dist: pytest-mock ; extra == 'test'
Requires-Dist: mock ; extra == 'test'
Requires-Dist: hypothesis ; extra == 'test'
Requires-Dist: scipy ; extra == 'test'
Requires-Dist: torchvision ; extra == 'test'
Provides-Extra: tts
Requires-Dist: soundfile ; extra == 'tts'
Requires-Dist: librosa ; extra == 'tts'
Requires-Dist: numpy ; extra == 'tts'
Requires-Dist: scipy ; extra == 'tts'
Requires-Dist: tqdm ; extra == 'tts'
Requires-Dist: pillow ; extra == 'tts'
Requires-Dist: pyyaml ; extra == 'tts'
Provides-Extra: vision
Requires-Dist: torchvision ; extra == 'vision'
